Metadata-Version: 1.1
Name: angryduckschool
Version: 0.6
Summary: OOP Learning Example by Angryduck
Home-page: https://github.com/angryduck888/angryduckschool
Author: Angryduck
Author-email: darkworld777@hotmail.com
License: MIT
Download-URL: https://github.com/angryduck888/angryduckschool/archive/v_05.tar.gz
Keywords: OOP Python,THAI,Angryduck
Platform: UNKNOWN
Classifier: Development Status :: 3 - Alpha
Classifier: Intended Audience :: Developers
Classifier: Topic :: Software Development :: Build Tools
Classifier: License :: OSI Approved :: MIT License
Classifier: Programming Language :: Python :: 3
Classifier: Programming Language :: Python :: 3.4
Classifier: Programming Language :: Python :: 3.5
Classifier: Programming Language :: Python :: 3.6
Classifier: Programming Language :: Python :: 3.7
Classifier: Programming Language :: Python :: 3.8
Classifier: Programming Language :: Python :: 3.9
